aioreq/__init__.py
aioreq/auth.py
aioreq/cli.py
aioreq/codes.py
aioreq/connection.py
aioreq/cookies.py
aioreq/encodings.py
aioreq/generic.py
aioreq/headers.py
aioreq/http.py
aioreq/middlewares.py
aioreq/parsers.py
aioreq/settings.ini
aioreq/settings.py
aioreq/urls.py
aioreq/errors/__init__.py
aioreq/errors/base.py
aioreq/errors/parser.py
aioreq/errors/requests.py
aioreq/errors/response.py
aioreq-1.0.7.dist-info/METADATA
aioreq-1.0.7.dist-info/WHEEL
aioreq-1.0.7.dist-info/entry_points.txt
aioreq-1.0.7.dist-info/licenses/LICENSE
aioreq-1.0.7.dist-info/RECORD
