Metadata-Version: 2.1
Name: aioreq
Version: 1.0.7
Summary: Asynchronous HTTP library.
Project-URL: Homepage, https://github.com/karosis88/aioerq
Project-URL: Source, https://github.com/karosis88/aioreq
License-File: LICENSE
Classifier: Framework :: AsyncIO
Classifier: License :: OSI Approved :: MIT License
Classifier: Natural Language :: English
Classifier: Programming Language :: Python :: 3.8
Classifier: Programming Language :: Python :: 3.9
Classifier: Programming Language :: Python :: 3.10
Classifier: Programming Language :: Python :: 3.11
Classifier: Programming Language :: Python :: Implementation :: CPython
Classifier: Topic :: Internet :: WWW/HTTP
Requires-Python: >=3.7
Requires-Dist: dnspython
Provides-Extra: uvloop
Requires-Dist: uvloop; extra == 'uvloop'
